AUTHORS.rst
LICENSE
README.rst
setup.cfg
setup.py
ecoute/__init__.py
ecoute/ecoute.py
ecoute/export.py
ecoute.egg-info/PKG-INFO
ecoute.egg-info/SOURCES.txt
ecoute.egg-info/dependency_links.txt
ecoute.egg-info/not-zip-safe
ecoute.egg-info/requires.txt
ecoute.egg-info/top_level.txt
tests/test_ecoute.py
tests/test_export.py