Metadata-Version: 2.1
Name: ecoute
Version: 0.1.2
Summary: Écoute is a wrapper on OpenAPI Whisper API. It's provide support for long audio files.
Home-page: https://github.com/julien-duponchelle/ecoute
Author: Julien Duponchelle
Author-email: julien@duponchelle.info
License: Apache Software License 2.0
Keywords: ecoute
Classifier: Development Status :: 2 - Pre-Alpha
Classifier: Intended Audience :: Developers
Classifier: License :: OSI Approved :: Apache Software License
Classifier: Natural Language :: English
Classifier: Programming Language :: Python :: 3
Classifier: Programming Language :: Python :: 3.5
Classifier: Programming Language :: Python :: 3.6
Classifier: Programming Language :: Python :: 3.7
Classifier: Programming Language :: Python :: 3.8
Classifier: Programming Language :: Python :: 3.9
Classifier: Programming Language :: Python :: 3.10
Classifier: Programming Language :: Python :: 3.11
Requires-Python: >=3.5
License-File: LICENSE
License-File: AUTHORS.rst
